odoo/addons/ssi_web_server_action_confirmation/README.rst
odoo/addons/ssi_web_server_action_confirmation/__init__.py
odoo/addons/ssi_web_server_action_confirmation/__manifest__.py
odoo/addons/ssi_web_server_action_confirmation/static/description/icon.png
odoo/addons/ssi_web_server_action_confirmation/static/src/js/action_manager.js
odoo/addons/ssi_web_server_action_confirmation/views/assets.xml
odoo14_addon_ssi_web_server_action_confirmation-14.0.1.0.1.dev4.dist-info/METADATA
odoo14_addon_ssi_web_server_action_confirmation-14.0.1.0.1.dev4.dist-info/WHEEL
odoo14_addon_ssi_web_server_action_confirmation-14.0.1.0.1.dev4.dist-info/top_level.txt
odoo14_addon_ssi_web_server_action_confirmation-14.0.1.0.1.dev4.dist-info/RECORD
